README.rst
setup.py
heman/__init__.py
heman/app.py
heman/config.py
heman/heman.py
heman.egg-info/PKG-INFO
heman.egg-info/SOURCES.txt
heman.egg-info/dependency_links.txt
heman.egg-info/requires.txt
heman.egg-info/top_level.txt
heman/api/__init__.py
heman/api/cch/__init__.py
heman/api/empowering/__init__.py
heman/api/empowering/base.py
heman/api/empowering/custom.py
heman/api/empowering/ot101.py
heman/api/empowering/ot103.py
heman/api/empowering/ot201.py
heman/api/empowering/ot401.py
heman/api/form/__init__.py
heman/auth/__init__.py