Metadata-Version: 1.0
Name: heman
Version: 0.3.0
Summary: He-Man
